brownian_stock/__init__.py
brownian_stock/const.py
brownian_stock/main.py
brownian_stock/simulator.py
brownian_stock/commands/__init__.py
brownian_stock/commands/download.py
brownian_stock/commands/generate.py
brownian_stock/data/calendar.json
brownian_stock/data/topix_universe.csv
brownian_stock/models/__init__.py
brownian_stock/models/abstract_model.py
brownian_stock/models/abstract_series.py
brownian_stock/models/account.py
brownian_stock/models/brand.py
brownian_stock/models/calendar.py
brownian_stock/models/index_series.py
brownian_stock/models/joined_index_series.py
brownian_stock/models/margin_series.py
brownian_stock/models/order.py
brownian_stock/models/pct_change_series.py
brownian_stock/models/return_map.py
brownian_stock/models/sector_code.py
brownian_stock/models/statements.py
brownian_stock/models/statements_report.py
brownian_stock/models/stock_series.py
brownian_stock/models/stock_set.py
brownian_stock/repository/__init__.py
brownian_stock/repository/brand_repository.py
brownian_stock/repository/index_csv_repository.py
brownian_stock/repository/margin_interest_sql_repository.py
brownian_stock/repository/pandastic.py
brownian_stock/repository/raw_brand_repository.py
brownian_stock/repository/raw_margin_interest_repository.py
brownian_stock/repository/raw_statements_repository.py
brownian_stock/repository/raw_stock_repository.py
brownian_stock/repository/repository_path.py
brownian_stock/repository/statements_csv_repository.py
brownian_stock/repository/statements_sql_repository.py
brownian_stock/repository/stock_csv_repository.py
brownian_stock/repository/stock_set_repository.py
brownian_stock/repository/stock_sql_repository.py
brownian_stock/schemas/__init__.py
brownian_stock/schemas/dynamic_typing.py
brownian_stock/schemas/schema_margin_interest.py
brownian_stock/schemas/schema_statements.py
brownian_stock/schemas/schema_stock.py
brownian_stock/schemas/schema_symbol.py
brownian_stock/schemas/sql.py
brownian_stock/schemas/types.py
brownian_stock-0.0.51.dist-info/METADATA
brownian_stock-0.0.51.dist-info/WHEEL
brownian_stock-0.0.51.dist-info/licenses/LICENSE.txt
brownian_stock-0.0.51.dist-info/RECORD
