Metadata-Version: 2.1
Name: brownian_stock
Version: 0.0.51
Summary: Add your description here
Author-email: Keisuke Miura <toritoritori29@gmail.com>
License-File: LICENSE.txt
Requires-Python: >=3.10
Requires-Dist: boto3>=1.26.129
Requires-Dist: bumpversion>=0.6.0
Requires-Dist: connectorx>=0.3.1
Requires-Dist: humanize>=4.6.0
Requires-Dist: matplotlib>=3.7.1
Requires-Dist: numpy>=1.23.5
Requires-Dist: pandas>=1.5.3
Requires-Dist: polars==0.19.11
Requires-Dist: pyarrow>=11.0.0
Requires-Dist: pydantic==1.10.7
Requires-Dist: python-dateutil>=2.8.2
Requires-Dist: pyyaml>=6.0
Requires-Dist: requests>=2.28.2
Requires-Dist: sqlalchemy>=1.4.0
Requires-Dist: tqdm>=4.65.0
Requires-Dist: yfinance>=0.2.13
